algorithms/__init__.py
algorithms/algorithm.py
algorithms/fs.py
algorithms/vs.py
algorithms/waa.py
functions/__init__.py
functions/learners_loss_function.py
functions/loss_function.py
online_predict-1.0.dist-info/METADATA
online_predict-1.0.dist-info/RECORD
online_predict-1.0.dist-info/WHEEL
online_predict-1.0.dist-info/top_level.txt
