Metadata-Version: 2.1
Name: online-predict
Version: 1.0
Summary: Python library for online prediction 
Home-page: https://github.com/songheony/online-predict
Author: Heon Song
Author-email: songheony@gmail.com
License: UNKNOWN
Download-URL: https://github.com/songheony/online-predict/archive/master.zip
Keywords: online_prediction
Platform: UNKNOWN
Classifier: Programming Language :: Python :: 3
Classifier: Programming Language :: Python :: 3.2
Classifier: Programming Language :: Python :: 3.3
Classifier: Programming Language :: Python :: 3.4
Classifier: Programming Language :: Python :: 3.5
Classifier: Programming Language :: Python :: 3.6
Requires-Python: >=3
